wasamole/__init__.py
wasamole/core/__init__.py
wasamole/core/elem.py
wasamole/core/exports.py
wasamole/core/function.py
wasamole/core/globalvar.py
wasamole/core/imports.py
wasamole/core/instructions.py
wasamole/core/localvar.py
wasamole/core/module.py
wasamole/core/types.py
wasamole/io/__init__.py
wasamole/io/reader/__init__.py
wasamole/io/reader/binary_format.py
wasamole/io/writer/__init__.py
wasamole/io/writer/text_format.py
wasamole/util/__init__.py
wasamole/util/bytes_reader.py
wasamole-0.5.0.data/scripts/wasm-objdump
wasamole-0.5.0.dist-info/LICENSE
wasamole-0.5.0.dist-info/METADATA
wasamole-0.5.0.dist-info/WHEEL
wasamole-0.5.0.dist-info/top_level.txt
wasamole-0.5.0.dist-info/RECORD
