Metadata-Version: 2.1
Name: wasamole
Version: 0.5.0
Summary: A tasty framework for WebAssembly Software Analysis
Home-page: https://github.com/CarveSystems/wasamole
Author: Carve Systems, LLC.
Author-email: meadori@carvesystems.com
License: MIT License
Platform: UNKNOWN
Classifier: Programming Language :: Python :: 3
Classifier: License :: OSI Approved :: MIT License
Classifier: Development Status :: 4 - Beta
Classifier: Operating System :: OS Independent
Classifier: Topic :: Security
Classifier: Topic :: Utilities
Classifier: Topic :: Software Development :: Assemblers
Classifier: Topic :: Software Development :: Disassemblers
Classifier: Topic :: Software Development :: Interpreters
Requires-Python: >=3.7
